src/seven_segment.v
module seven_segment_display (
    input wire [7:0] char,   // ASCII character input
    output reg [6:0] seg     // 7-segment output
);

    always @(*) begin
        case (char)
            "A": seg = 7'b0111111;
            "B": seg = 7'b0000111;
            "C": seg = 7'b1001110;
            "D": seg = 7'b0111101;
            "E": seg = 7'b1001111;
            "F": seg = 7'b1000111;
            // Add all relevant characters for display...
            default: seg = 7'b0000000; // Blank display for unsupported chars
        endcase
    end

endmodule

src/morse_decode.v
module morse_decoder (
    input wire clk,
    input wire rst_n,
    input wire [1:0] morse_signal,
    output reg [7:0] decoded_char
);

    reg [5:0] morse_seq;  // Sequence of dots/dashes (up to 6 bits)

    always @(posedge clk or negedge rst_n) begin
        if (!rst_n) begin
            morse_seq <= 6'b0;
            decoded_char <= 8'b0;
        end else begin
            // Update sequence with new dot/dash
            if (morse_signal == 2'b01 || morse_signal == 2'b10) begin
                morse_seq <= {morse_seq[4:0], morse_signal[0]};  // Shift sequence
            end

            // On space or end of sequence, decode the character
           case (morse_seq)
            6'b01_00_00: decoded_char <= "A";  // .-
            6'b10_00_00: decoded_char <= "B";  // -...
            6'b10_10_00: decoded_char <= "C";  // -.-.
            6'b10_01_00: decoded_char <= "D";  // -..
            6'b00_00_00: decoded_char <= "E";  // .
            6'b01_10_00: decoded_char <= "F";  // ..-.
            6'b10_10_10: decoded_char <= "G";  // --.
            6'b01_01_00: decoded_char <= "H";  // ....
            6'b01_00_00: decoded_char <= "I";  // ..
            6'b01_11_11: decoded_char <= "J";  // .---
            6'b10_01_10: decoded_char <= "K";  // -.-
            6'b01_10_01: decoded_char <= "L";  // .-..
            6'b10_10_00: decoded_char <= "M";  // --
            6'b10_00_00: decoded_char <= "N";  // -.
            6'b10_10_10: decoded_char <= "O";  // ---
            6'b01_11_10: decoded_char <= "P";  // .--.
            6'b10_10_01: decoded_char <= "Q";  // --.-
            6'b01_10_00: decoded_char <= "R";  // .-.
            6'b01_01_00: decoded_char <= "S";  // ...
            6'b10_00_00: decoded_char <= "T";  // -
            6'b01_01_10: decoded_char <= "U";  // ..-
            6'b01_01_01: decoded_char <= "V";  // ...-
            6'b01_11_00: decoded_char <= "W";  // .--
            6'b10_01_01: decoded_char <= "X";  // -..-
            6'b10_01_11: decoded_char <= "Y";  // -.--
            6'b10_10_01: decoded_char <= "Z";  // --..
            default: decoded_char <= 8'h00;    // Unknown
            endcase
        end
    end

endmodule

src/button_input.v
module button_input (
    input wire clk,
    input wire rst_n,
    input wire button,
    output reg [1:0] morse_signal // 00: no input, 01: dot, 10: dash
);

    reg [31:0] counter;        // To measure button press duration
    reg button_released;       // Track if the button was released

    always @(posedge clk or negedge rst_n) begin
        if (!rst_n) begin
            morse_signal <= 2'b00;
            counter <= 32'b0;
            button_released <= 1'b1;  // Initialize as "released"
        end else begin
            if (button) begin
                counter <= counter + 1;       // Increment counter while button is pressed
                button_released <= 1'b0;      // Button is held down
            end else if (!button && !button_released) begin
                // Check if button was released after being pressed

                // Adjust the threshold based on clock cycles
                if (counter >= 2000)  // Dash threshold
                    morse_signal <= 2'b10;  // Dash
                else if (counter < 100) // Adjust lower threshold for dot
                    morse_signal <= 2'b01;  // Dot
                else
                    morse_signal <= 2'b00;  // No input (invalid press)

                // Reset for the next button press
                counter <= 32'b0;
                button_released <= 1'b1;  // Button is now released
            end else begin
                morse_signal <= 2'b00;  // No input while button is not pressed
            end
        end
    end

endmodule

src/tt_um_morse_code.v
module tt_um_morse_code (
    input wire clk,
    input wire rst_n,
    input wire [7:0] ui_in,
    output wire [7:0] uo_out,
    output wire [7:0] uio_out,
    output wire [7:0] uio_oe,
    input wire [7:0] uio_in,
    input wire ena
);
    // Internal signals
    wire [1:0] morse_signal;
    wire [7:0] decoded_char;
    wire [6:0] seg;

    // Button input logic (ui_in[0] used for button input)
    button_input button_inst (
        .clk(clk),
        .rst_n(rst_n),
        .button(ui_in[0]),
        .morse_signal(morse_signal)
    );

    // Morse code decoder logic
    morse_decoder decoder_inst (
        .clk(clk),
        .rst_n(rst_n),
        .morse_signal(morse_signal),
        .decoded_char(decoded_char)
    );

    // Seven-segment display logic
    seven_segment_display display_inst (
        .char(decoded_char[7:0]), // Ensure 8-bit input
        .seg(seg)
    );

    // Outputs
    assign uo_out = 8'b0; // Not used in this project
    assign uio_out = {1'b0, seg}; // Only 7 bits are used for the 7-segment display
    assign uio_oe = 8'b11111111; // Output enable all bits

endmodule

test/tb.v
`timescale 1ns/1ps

module tb;

    // Testbench signals
    reg clk;
    reg rst_n;
    reg [7:0] ui_in;
    wire [7:0] uo_out;
    wire [7:0] uio_out;
    wire [7:0] uio_oe;
    reg [7:0] uio_in;
    reg ena;

    // Instantiate the top-level module
    tt_um_morse_code dut (
        .clk(clk),
        .rst_n(rst_n),
        .ui_in(ui_in),
        .uo_out(uo_out),
        .uio_out(uio_out),
        .uio_oe(uio_oe),
        .uio_in(uio_in),
        .ena(ena)
    );

    // Clock generation
    initial begin
        clk = 0;
        forever #5 clk = ~clk; // 100 MHz clock
    end

    // VCD dump logic (move to separate initial block)
    initial begin
        $dumpfile("dump.vcd");    // Specify the name of the VCD file
        $dumpvars(0, tb);         // Dump all variables in the tb module
    end

    // Simulation logic
    initial begin
        // Initialize inputs
        rst_n = 0;
        ui_in = 8'b0;
        uio_in = 8'b0;
        ena = 1'b1;

        // Reset the design
        #10 rst_n = 1;

        // Simulate Morse code for "A" (.-)

        // Dot (short press)
        ui_in[0] = 1'b1;  // Button pressed
        #100_000;         // Hold for 100_000 ns (dot duration)
        ui_in[0] = 1'b0;  // Button released
        #50_000;          // Wait 50_000 ns between symbols

        // Dash (long press)
        ui_in[0] = 1'b1;  // Button pressed
        #300_000;         // Hold for 300_000 ns (dash duration)
        ui_in[0] = 1'b0;  // Button released
        #500_000;         // Wait after character entry


        // End simulation
        #1_000_000;
        $finish;
    end
endmodule

test/dump.vcd
$date
	Tue Oct 22 10:38:16 2024
$end
$version
	Icarus Verilog
$end
$timescale
	1ps
$end
$scope module tb $end
$var wire 8 ! uio_oe [7:0] $end
$var wire 8 " uo_out [7:0] $end
$var wire 8 # uio_out [7:0] $end
$var reg 1 $ clk $end
$var reg 1 % ena $end
$var reg 1 & rst_n $end
$var reg 8 ' ui_in [7:0] $end
$var reg 8 ( uio_in [7:0] $end
$scope module dut $end
$var wire 1 $ clk $end
$var wire 1 % ena $end
$var wire 1 & rst_n $end
$var wire 8 ) ui_in [7:0] $end
$var wire 8 * uio_in [7:0] $end
$var wire 8 + uio_oe [7:0] $end
$var wire 8 , uo_out [7:0] $end
$var wire 8 - uio_out [7:0] $end
$var wire 7 . seg [6:0] $end
$var wire 2 / morse_signal [1:0] $end
$var wire 8 0 decoded_char [7:0] $end
$scope module button_inst $end
$var wire 1 1 button $end
$var wire 1 $ clk $end
$var wire 1 & rst_n $end
$var reg 1 2 button_released $end
$var reg 32 3 counter [31:0] $end
$var reg 2 4 morse_signal [1:0] $end
$upscope $end
$scope module decoder_inst $end
$var wire 1 $ clk $end
$var wire 2 5 morse_signal [1:0] $end
$var wire 1 & rst_n $end
$var reg 8 6 decoded_char [7:0] $end
$var reg 6 7 morse_seq [5:0] $end
$upscope $end
$scope module display_inst $end
$var wire 8 8 char [7:0] $end
$var reg 7 9 seg [6:0] $end
$upscope $end
$upscope $end
$upscope $end
$enddefinitions $end
$comment Show the parameter values. $end
$dumpall
$end
#0
$dumpvars
b0 9
b0 8
b0 7
b0 6
b0 5
b0 4
b0 3
12
01
b0 0
b0 /
b0 .
b0 -
b0 ,
b11111111 +
b0 *
b0 )
b0 (
b0 '
0&
1%
1$
b0 #
b0 "
b11111111 !
$end
#5000
0$
#10000
b1001111 #
b1001111 -
b1001111 .
b1001111 9
02
b1 3
b1000101 0
b1000101 6
b1000101 8
11
1$
b1 '
b1 )
1&
#15000
0$
#20000
b10 3
1$
#25000
0$
#30000
b11 3
1$
#35000
0$
#40000
b100 3
1$
#45000
0$
#50000
b101 3
1$
#55000
0$
#60000
b110 3
1$
#65000
0$
#70000
b111 3
1$
#75000
0$
#80000
b1000 3
1$
#85000
0$
#90000
b1001 3
1$
#95000
0$
#100000
b1010 3
1$
#105000
0$
#110000
b1011 3
1$
#115000
0$
#120000
b1100 3
1$
#125000
0$
#130000
b1101 3
1$
#135000
0$
#140000
b1110 3
1$
#145000
0$
#150000
b1111 3
1$
#155000
0$
#160000
b10000 3
1$
#165000
0$
#170000
b10001 3
1$
#175000
0$
#180000
b10010 3
1$
#185000
0$
#190000
b10011 3
1$
#195000
0$
#200000
b10100 3
1$
#205000
0$
#210000
b10101 3
1$
#215000
0$
#220000
b10110 3
1$
#225000
0$
#230000
b10111 3
1$
#235000
0$
#240000
b11000 3
1$
#245000
0$
#250000
b11001 3
1$
#255000
0$
#260000
b11010 3
1$
#265000
0$
#270000
b11011 3
1$
#275000
0$
#280000
b11100 3
1$
#285000
0$
#290000
b11101 3
1$
#295000
0$
#300000
b11110 3
1$
#305000
0$
#310000
b11111 3
1$
#315000
0$
#320000
b100000 3
1$
#325000
0$
#330000
b100001 3
1$
#335000
0$
#340000
b100010 3
1$
#345000
0$
#350000
b100011 3
1$
#355000
0$
#360000
b100100 3
1$
#365000
0$
#370000
b100101 3
1$
#375000
0$
#380000
b100110 3
1$
#385000
0$
#390000
b100111 3
1$
#395000
0$
#400000
b101000 3
1$
#405000
0$
#410000
b101001 3
1$
#415000
0$
#420000
b101010 3
1$
#425000
0$
#430000
b101011 3
1$
#435000
0$
#440000
b101100 3
1$
#445000
0$
#450000
b101101 3
1$
#455000
0$
#460000
b101110 3
1$
#465000
0$
#470000
b101111 3
1$
#475000
0$
#480000
b110000 3
1$
#485000
0$
#490000
b110001 3
1$
#495000
0$
#500000
b110010 3
1$
#505000
0$
#510000
b110011 3
1$
#515000
0$
#520000
b110100 3
1$
#525000
0$
#530000
b110101 3
1$
#535000
0$
#540000
b110110 3
1$
#545000
0$
#550000
b110111 3
1$
#555000
0$
#560000
b111000 3
1$
#565000
0$
#570000
b111001 3
1$
#575000
0$
#580000
b111010 3
1$
#585000
0$
#590000
b111011 3
1$
#595000
0$
#600000
b111100 3
1$
#605000
0$
#610000
b111101 3
1$
#615000
0$
#620000
b111110 3
1$
#625000
0$
#630000
b111111 3
1$
#635000
0$
#640000
b1000000 3
1$
#645000
0$
#650000
b1000001 3
1$
#655000
0$
#660000
b1000010 3
1$
#665000
0$
#670000
b1000011 3
1$
#675000
0$
#680000
b1000100 3
1$
#685000
0$
#690000
b1000101 3
1$
#695000
0$
#700000
b1000110 3
1$
#705000
0$
#710000
b1000111 3
1$
#715000
0$
#720000
b1001000 3
1$
#725000
0$
#730000
b1001001 3
1$
#735000
0$
#740000
b1001010 3
1$
#745000
0$
#750000
b1001011 3
1$
#755000
0$
#760000
b1001100 3
1$
#765000
0$
#770000
b1001101 3
1$
#775000
0$
#780000
b1001110 3
1$
#785000
0$
#790000
b1001111 3
1$
#795000
0$
#800000
b1010000 3
1$
#805000
0$
#810000
b1010001 3
1$
#815000
0$
#820000
b1010010 3
1$
#825000
0$
#830000
b1010011 3
1$
#835000
0$
#840000
b1010100 3
1$
#845000
0$
#850000
b1010101 3
1$
#855000
0$
#860000
b1010110 3
1$
#865000
0$
#870000
b1010111 3
1$
#875000
0$
#880000
b1011000 3
1$
#885000
0$
#890000
b1011001 3
1$
#895000
0$
#900000
b1011010 3
1$
#905000
0$
#910000
b1011011 3
1$
#915000
0$
#920000
b1011100 3
1$
#925000
0$
#930000
b1011101 3
1$
#935000
0$
#940000
b1011110 3
1$
#945000
0$
#950000
b1011111 3
1$
#955000
0$
#960000
b1100000 3
1$
#965000
0$
#970000
b1100001 3
1$
#975000
0$
#980000
b1100010 3
1$
#985000
0$
#990000
b1100011 3
1$
#995000
0$
#1000000
b1100100 3
1$
#1005000
0$
#1010000
b1100101 3
1$
#1015000
0$
#1020000
b1100110 3
1$
#1025000
0$
#1030000
b1100111 3
1$
#1035000
0$
#1040000
b1101000 3
1$
#1045000
0$
#1050000
b1101001 3
1$
#1055000
0$
#1060000
b1101010 3
1$
#1065000
0$
#1070000
b1101011 3
1$
#1075000
0$
#1080000
b1101100 3
1$
#1085000
0$
#1090000
b1101101 3
1$
#1095000
0$
#1100000
b1101110 3
1$
#1105000
0$
#1110000
b1101111 3
1$
#1115000
0$
#1120000
b1110000 3
1$
#1125000
0$
#1130000
b1110001 3
1$
#1135000
0$
#1140000
b1110010 3
1$
#1145000
0$
#1150000
b1110011 3
1$
#1155000
0$
#1160000
b1110100 3
1$
#1165000
0$
#1170000
b1110101 3
1$
#1175000
0$
#1180000
b1110110 3
1$
#1185000
0$
#1190000
b1110111 3
1$
#1195000
0$
#1200000
b1111000 3
1$
#1205000
0$
#1210000
b1111001 3
1$
#1215000
0$
#1220000
b1111010 3
1$
#1225000
0$
#1230000
b1111011 3
1$
#1235000
0$
#1240000
b1111100 3
1$
#1245000
0$
#1250000
b1111101 3
1$
#1255000
0$
#1260000
b1111110 3
1$
#1265000
0$
#1270000
b1111111 3
1$
#1275000
0$
#1280000
b10000000 3
1$
#1285000
0$
#1290000
b10000001 3
1$
#1295000
0$
#1300000
b10000010 3
1$
#1305000
0$
#1310000
b10000011 3
1$
#1315000
0$
#1320000
b10000100 3
1$
#1325000
0$
#1330000
b10000101 3
1$
#1335000
0$
#1340000
b10000110 3
1$
#1345000
0$
#1350000
b10000111 3
1$
#1355000
0$
#1360000
b10001000 3
1$
#1365000
0$
#1370000
b10001001 3
1$
#1375000
0$
#1380000
b10001010 3
1$
#1385000
0$
#1390000
b10001011 3
1$
#1395000
0$
#1400000
b10001100 3
1$
#1405000
0$
#1410000
b10001101 3
1$
#1415000
0$
#1420000
b10001110 3
1$
#1425000
0$
#1430000
b10001111 3
1$
#1435000
0$
#1440000
b10010000 3
1$
#1445000
0$
#1450000
b10010001 3
1$
#1455000
0$
#1460000
b10010010 3
1$
#1465000
0$
#1470000
b10010011 3
1$
#1475000
0$
#1480000
b10010100 3
1$
#1485000
0$
#1490000
b10010101 3
1$
#1495000
0$
#1500000
b10010110 3
1$
#1505000
0$
#1510000
b10010111 3
1$
#1515000
0$
#1520000
b10011000 3
1$
#1525000
0$
#1530000
b10011001 3
1$
#1535000
0$
#1540000
b10011010 3
1$
#1545000
0$
#1550000
b10011011 3
1$
#1555000
0$
#1560000
b10011100 3
1$
#1565000
0$
#1570000
b10011101 3
1$
#1575000
0$
#1580000
b10011110 3
1$
#1585000
0$
#1590000
b10011111 3
1$
#1595000
0$
#1600000
b10100000 3
1$
#1605000
0$
#1610000
b10100001 3
1$
#1615000
0$
#1620000
b10100010 3
1$
#1625000
0$
#1630000
b10100011 3
1$
#1635000
0$
#1640000
b10100100 3
1$
#1645000
0$
#1650000
b10100101 3
1$
#1655000
0$
#1660000
b10100110 3
1$
#1665000
0$
#1670000
b10100111 3
1$
#1675000
0$
#1680000
b10101000 3
1$
#1685000
0$
#1690000
b10101001 3
1$
#1695000
0$
#1700000
b10101010 3
1$
#1705000
0$
#1710000
b10101011 3
1$
#1715000
0$
#1720000
b10101100 3
1$
#1725000
0$
#1730000
b10101101 3
1$
#1735000
0$
#1740000
b10101110 3
1$
#1745000
0$
#1750000
b10101111 3
1$
#1755000
0$
#1760000
b10110000 3
1$
#1765000
0$
#1770000
b10110001 3
1$
#1775000
0$
#1780000
b10110010 3
1$
#1785000
0$
#1790000
b10110011 3
1$
#1795000
0$
#1800000
b10110100 3
1$
#1805000
0$
#1810000
b10110101 3
1$
#1815000
0$
#1820000
b10110110 3
1$
#1825000
0$
#1830000
b10110111 3
1$
#1835000
0$
#1840000
b10111000 3
1$
#1845000
0$
#1850000
b10111001 3
1$
#1855000
0$
#1860000
b10111010 3
1$
#1865000
0$
#1870000
b10111011 3
1$
#1875000
0$
#1880000
b10111100 3
1$
#1885000
0$
#1890000
b10111101 3
1$
#1895000
0$
#1900000
b10111110 3
1$
#1905000
0$
#1910000
b10111111 3
1$
#1915000
0$
#1920000
b11000000 3
1$
#1925000
0$
#1930000
b11000001 3
1$
#1935000
0$
#1940000
b11000010 3
1$
#1945000
0$
#1950000
b11000011 3
1$
#1955000
0$
#1960000
b11000100 3
1$
#1965000
0$
#1970000
b11000101 3
1$
#1975000
0$
#1980000
b11000110 3
1$
#1985000
0$
#1990000
b11000111 3
1$
#1995000
0$
#2000000
b11001000 3
1$
#2005000
0$
#2010000
b11001001 3
1$
#2015000
0$
#2020000
b11001010 3
1$
#2025000
0$
#2030000
b11001011 3
1$
#2035000
0$
#2040000
b11001100 3
1$
#2045000
0$
#2050000
b11001101 3
1$
#2055000
0$
#2060000
b11001110 3
1$
#2065000
0$
#2070000
b11001111 3
1$
#2075000
0$
#2080000
b11010000 3
1$
#2085000
0$
#2090000
b11010001 3
1$
#2095000
0$
#2100000
b11010010 3
1$
#2105000
0$
#2110000
b11010011 3
1$
#2115000
0$
#2120000
b11010100 3
1$
#2125000
0$
#2130000
b11010101 3
1$
#2135000
0$
#2140000
b11010110 3
1$
#2145000
0$
#2150000
b11010111 3
1$
#2155000
0$
#2160000
b11011000 3
1$
#2165000
0$
#2170000
b11011001 3
1$
#2175000
0$
#2180000
b11011010 3
1$
#2185000
0$
#2190000
b11011011 3
1$
#2195000
0$
#2200000
b11011100 3
1$
#2205000
0$
#2210000
b11011101 3
1$
#2215000
0$
#2220000
b11011110 3
1$
#2225000
0$
#2230000
b11011111 3
1$
#2235000
0$
#2240000
b11100000 3
1$
#2245000
0$
#2250000
b11100001 3
1$
#2255000
0$
#2260000
b11100010 3
1$
#2265000
0$
#2270000
b11100011 3
1$
#2275000
0$
#2280000
b11100100 3
1$
#2285000
0$
#2290000
b11100101 3
1$
#2295000
0$
#2300000
b11100110 3
1$
#2305000
0$
#2310000
b11100111 3
1$
#2315000
0$
#2320000
b11101000 3
1$
#2325000
0$
#2330000
b11101001 3
1$
#2335000
0$
#2340000
b11101010 3
1$
#2345000
0$
#2350000
b11101011 3
1$
#2355000
0$
#2360000
b11101100 3
1$
#2365000
0$
#2370000
b11101101 3
1$
#2375000
0$
#2380000
b11101110 3
1$
#2385000
0$
#2390000
b11101111 3
1$
#2395000
0$
#2400000
b11110000 3
1$
#2405000
0$
#2410000
b11110001 3
1$
#2415000
0$
#2420000
b11110010 3
1$
#2425000
0$
#2430000
b11110011 3
1$
#2435000
0$
#2440000
b11110100 3
1$
#2445000
0$
#2450000
b11110101 3
1$
#2455000
0$
#2460000
b11110110 3
1$
#2465000
0$
#2470000
b11110111 3
1$
#2475000
0$
#2480000
b11111000 3
1$
#2485000
0$
#2490000
b11111001 3
1$
#2495000
0$
#2500000
b11111010 3
1$
#2505000
0$
#2510000
b11111011 3
1$
#2515000
0$
#2520000
b11111100 3
1$
#2525000
0$
#2530000
b11111101 3
1$
#2535000
0$
#2540000
b11111110 3
1$
#2545000
0$
#2550000
b11111111 3
1$
#2555000
0$
#2560000
b100000000 3
1$
#2565000
0$
#2570000
b100000001 3
1$
#2575000
0$
#2580000
b100000010 3
1$
#2585000
0$
#2590000
b100000011 3
1$
#2595000
0$
#2600000
b100000100 3
1$
#2605000
0$
#2610000
b100000101 3
1$
#2615000
0$
#2620000
b100000110 3
1$
#2625000
0$
#2630000
b100000111 3
1$
#2635000
0$
#2640000
b100001000 3
1$
#2645000
0$
#2650000
b100001001 3
1$
#2655000
0$
#2660000
b100001010 3
1$
#2665000
0$
#2670000
b100001011 3
1$
#2675000
0$
#2680000
b100001100 3
1$
#2685000
0$
#2690000
b100001101 3
1$
#2695000
0$
#2700000
b100001110 3
1$
#2705000
0$
#2710000
b100001111 3
1$
#2715000
0$
#2720000
b100010000 3
1$
#2725000
0$
#2730000
b100010001 3
1$
#2735000
0$
#2740000
b100010010 3
1$
#2745000
0$
#2750000
b100010011 3
1$
#2755000
0$
#2760000
b100010100 3
1$
#2765000
0$
#2770000
b100010101 3
1$
#2775000
0$
#2780000
b100010110 3
1$
#2785000
0$
#2790000
b100010111 3
1$
#2795000
0$
#2800000
b100011000 3
1$
#2805000
0$
#2810000
b100011001 3
1$
#2815000
0$
#2820000
b100011010 3
1$
#2825000
0$
#2830000
b100011011 3
1$
#2835000
0$
#2840000
b100011100 3
1$
#2845000
0$
#2850000
b100011101 3
1$
#2855000
0$
#2860000
b100011110 3
1$
#2865000
0$
#2870000
b100011111 3
1$
#2875000
0$
#2880000
b100100000 3
1$
#2885000
0$
#2890000
b100100001 3
1$
#2895000
0$
#2900000
b100100010 3
1$
#2905000
0$
#2910000
b100100011 3
1$
#2915000
0$
#2920000
b100100100 3
1$
#2925000
0$
#2930000
b100100101 3
1$
#2935000
0$
#2940000
b100100110 3
1$
#2945000
0$
#2950000
b100100111 3
1$
#2955000
0$
#2960000
b100101000 3
1$
#2965000
0$
#2970000
b100101001 3
1$
#2975000
0$
#2980000
b100101010 3
1$
#2985000
0$
#2990000
b100101011 3
1$
#2995000
0$
#3000000
b100101100 3
1$
#3005000
0$
#3010000
b100101101 3
1$
#3015000
0$
#3020000
b100101110 3
1$
#3025000
0$
#3030000
b100101111 3
1$
#3035000
0$
#3040000
b100110000 3
1$
#3045000
0$
#3050000
b100110001 3
1$
#3055000
0$
#3060000
b100110010 3
1$
#3065000
0$
#3070000
b100110011 3
1$
#3075000
0$
#3080000
b100110100 3
1$
#3085000
0$
#3090000
b100110101 3
1$
#3095000
0$
#3100000
b100110110 3
1$
#3105000
0$
#3110000
b100110111 3
1$
#3115000
0$
#3120000
b100111000 3
1$
#3125000
0$
#3130000
b100111001 3
1$
#3135000
0$
#3140000
b100111010 3
1$
#3145000
0$
#3150000
b100111011 3
1$
#3155000
0$
#3160000
b100111100 3
1$
#3165000
0$
#3170000
b100111101 3
1$
#3175000
0$
#3180000
b100111110 3
1$
#3185000
0$
#3190000
b100111111 3
1$
#3195000
0$
#3200000
b101000000 3
1$
#3205000
0$
#3210000
b101000001 3
1$
#3215000
0$
#3220000
b101000010 3
1$
#3225000
0$
#3230000
b101000011 3
1$
#3235000
0$
#3240000
b101000100 3
1$
#3245000
0$
#3250000
b101000101 3
1$
#3255000
0$
#3260000
b101000110 3
1$
#3265000
0$
#3270000
b101000111 3
1$
#3275000
0$
#3280000
b101001000 3
1$
#3285000
0$
#3290000
b101001001 3
1$
#3295000
0$
#3300000
b101001010 3
1$
#3305000
0$
#3310000
b101001011 3
1$
#3315000
0$
#3320000
b101001100 3
1$
#3325000
0$
#3330000
b101001101 3
1$
#3335000
0$
#3340000
b101001110 3
1$
#3345000
0$
#3350000
b101001111 3
1$
#3355000
0$
#3360000
b101010000 3
1$
#3365000
0$
#3370000
b101010001 3
1$
#3375000
0$
#3380000
b101010010 3
1$
#3385000
0$
#3390000
b101010011 3
1$
#3395000
0$
#3400000
b101010100 3
1$
#3405000
0$
#3410000
b101010101 3
1$
#3415000
0$
#3420000
b101010110 3
1$
#3425000
0$
#3430000
b101010111 3
1$
#3435000
0$
#3440000
b101011000 3
1$
#3445000
0$
#3450000
b101011001 3
1$
#3455000
0$
#3460000
b101011010 3
1$
#3465000
0$
#3470000
b101011011 3
1$
#3475000
0$
#3480000
b101011100 3
1$
#3485000
0$
#3490000
b101011101 3
1$
#3495000
0$
#3500000
b101011110 3
1$
#3505000
0$
#3510000
b101011111 3
1$
#3515000
0$
#3520000
b101100000 3
1$
#3525000
0$
#3530000
b101100001 3
1$
#3535000
0$
#3540000
b101100010 3
1$
#3545000
0$
#3550000
b101100011 3
1$
#3555000
0$
#3560000
b101100100 3
1$
#3565000
0$
#3570000
b101100101 3
1$
#3575000
0$
#3580000
b101100110 3
1$
#3585000
0$
#3590000
b101100111 3
1$
#3595000
0$
#3600000
b101101000 3
1$
#3605000
0$
#3610000
b101101001 3
1$
#3615000
0$
#3620000
b101101010 3
1$
#3625000
0$
#3630000
b101101011 3
1$
#3635000
0$
#3640000
b101101100 3
1$
#3645000
0$
#3650000
b101101101 3
1$
#3655000
0$
#3660000
b101101110 3
1$
#3665000
0$
#3670000
b101101111 3
1$
#3675000
0$
#3680000
b101110000 3
1$
#3685000
0$
#3690000
b101110001 3
1$
#3695000
0$
#3700000
b101110010 3
1$
#3705000
0$
#3710000
b101110011 3
1$
#3715000
0$
#3720000
b101110100 3
1$
#3725000
0$
#3730000
b101110101 3
1$
#3735000
0$
#3740000
b101110110 3
1$
#3745000
0$
#3750000
b101110111 3
1$
#3755000
0$
#3760000
b101111000 3
1$
#3765000
0$
#3770000
b101111001 3
1$
#3775000
0$
#3780000
b101111010 3
1$
#3785000
0$
#3790000
b101111011 3
1$
#3795000
0$
#3800000
b101111100 3
1$
#3805000
0$
#3810000
b101111101 3
1$
#3815000
0$
#3820000
b101111110 3
1$
#3825000
0$
#3830000
b101111111 3
1$
#3835000
0$
#3840000
b110000000 3
1$
#3845000
0$
#3850000
b110000001 3
1$
#3855000
0$
#3860000
b110000010 3
1$
#3865000
0$
#3870000
b110000011 3
1$
#3875000
0$
#3880000
b110000100 3
1$
#3885000
0$
#3890000
b110000101 3
1$
#3895000
0$
#3900000
b110000110 3
1$
#3905000
0$
#3910000
b110000111 3
1$
#3915000
0$
#3920000
b110001000 3
1$
#3925000
0$
#3930000
b110001001 3
1$
#3935000
0$
#3940000
b110001010 3
1$
#3945000
0$
#3950000
b110001011 3
1$
#3955000
0$
#3960000
b110001100 3
1$
#3965000
0$
#3970000
b110001101 3
1$
#3975000
0$
#3980000
b110001110 3
1$
#3985000
0$
#3990000
b110001111 3
1$
#3995000
0$
#4000000
b110010000 3
1$
#4005000
0$
#4010000
b110010001 3
1$
#4015000
0$
#4020000
b110010010 3
1$
#4025000
0$
#4030000
b110010011 3
1$
#4035000
0$
#4040000
b110010100 3
1$
#4045000
0$
#4050000
b110010101 3
1$
#4055000
0$
#4060000
b110010110 3
1$
#4065000
0$
#4070000
b110010111 3
1$
#4075000
0$
#4080000
b110011000 3
1$
#4085000
0$
#4090000
b110011001 3
1$
#4095000
0$
#4100000
b110011010 3
1$
#4105000
0$
#4110000
b110011011 3
1$
#4115000
0$
#4120000
b110011100 3
1$
#4125000
0$
#4130000
b110011101 3
1$
#4135000
0$
#4140000
b110011110 3
1$
#4145000
0$
#4150000
b110011111 3
1$
#4155000
0$
#4160000
b110100000 3
1$
#4165000
0$
#4170000
b110100001 3
1$
#4175000
0$
#4180000
b110100010 3
1$
#4185000
0$
#4190000
b110100011 3
1$
#4195000
0$
#4200000
b110100100 3
1$
#4205000
0$
#4210000
b110100101 3
1$
#4215000
0$
#4220000
b110100110 3
1$
#4225000
0$
#4230000
b110100111 3
1$
#4235000
0$
#4240000
b110101000 3
1$
#4245000
0$
#4250000
b110101001 3
1$
#4255000
0$
#4260000
b110101010 3
1$
#4265000
0$
#4270000
b110101011 3
1$
#4275000
0$
#4280000
b110101100 3
1$
#4285000
0$
#4290000
b110101101 3
1$
#4295000
0$
#4300000
b110101110 3
1$
#4305000
0$
#4310000
b110101111 3
1$
#4315000
0$
#4320000
b110110000 3
1$
#4325000
0$
#4330000
b110110001 3
1$
#4335000
0$
#4340000
b110110010 3
1$
#4345000
0$
#4350000
b110110011 3
1$
#4355000
0$
#4360000
b110110100 3
1$
#4365000
0$
#4370000
b110110101 3
1$
#4375000
0$
#4380000
b110110110 3
1$
#4385000
0$
#4390000
b110110111 3
1$
#4395000
0$
#4400000
b110111000 3
1$
#4405000
0$
#4410000
b110111001 3
1$
#4415000
0$
#4420000
b110111010 3
1$
#4425000
0$
#4430000
b110111011 3
1$
#4435000
0$
#4440000
b110111100 3
1$
#4445000
0$
#4450000
b110111101 3
1$
#4455000
0$
#4460000
b110111110 3
1$
#4465000
0$
#4470000
b110111111 3
1$
#4475000
0$
#4480000
b111000000 3
1$
#4485000
0$
#4490000
b111000001 3
1$
#4495000
0$
#4500000
b111000010 3
1$
#4505000
0$
#4510000
b111000011 3
1$
#4515000
0$
#4520000
b111000100 3
1$
#4525000
0$
#4530000
b111000101 3
1$
#4535000
0$
#4540000
b111000110 3
1$
#4545000
0$
#4550000
b111000111 3
1$
#4555000
0$
#4560000
b111001000 3
1$
#4565000
0$
#4570000
b111001001 3
1$
#4575000
0$
#4580000
b111001010 3
1$
#4585000
0$
#4590000
b111001011 3
1$
#4595000
0$
#4600000
b111001100 3
1$
#4605000
0$
#4610000
b111001101 3
1$
#4615000
0$
#4620000
b111001110 3
1$
#4625000
0$
#4630000
b111001111 3
1$
#4635000
0$
#4640000
b111010000 3
1$
#4645000
0$
#4650000
b111010001 3
1$
#4655000
0$
#4660000
b111010010 3
1$
#4665000
0$
#4670000
b111010011 3
1$
#4675000
0$
#4680000
b111010100 3
1$
#4685000
0$
#4690000
b111010101 3
1$
#4695000
0$
#4700000
b111010110 3
1$
#4705000
0$
#4710000
b111010111 3
1$
#4715000
0$
#4720000
b111011000 3
1$
#4725000
0$
#4730000
b111011001 3
1$
#4735000
0$
#4740000
b111011010 3
1$
#4745000
0$
#4750000
b111011011 3
1$
#4755000
0$
#4760000
b111011100 3
1$
#4765000
0$
#4770000
b111011101 3
1$
#4775000
0$
#4780000
b111011110 3
1$
#4785000
0$
#4790000
b111011111 3
1$
#4795000
0$
#4800000
b111100000 3
1$
#4805000
0$
#4810000
b111100001 3
1$
#4815000
0$
#4820000
b111100010 3
1$
#4825000
0$
#4830000
b111100011 3
1$
#4835000
0$
#4840000
b111100100 3
1$
#4845000
0$
#4850000
b111100101 3
1$
#4855000
0$
#4860000
b111100110 3
1$
#4865000
0$
#4870000
b111100111 3
1$
#4875000
0$
#4880000
b111101000 3
1$
#4885000
0$
#4890000
b111101001 3
1$
#4895000
0$
#4900000
b111101010 3
1$
#4905000
0$
#4910000
b111101011 3
1$
#4915000
0$
#4920000
b111101100 3
1$
#4925000
0$
#4930000
b111101101 3
1$
#4935000
0$
